[
  {
    "type": "Title",
    "element_id": "0a77ced28c402390c2835b9305b0b041",
    "text": "57 Appointment of Curators in Respect of Persons under Disability and Release from Curatorship",
    "metadata": {
      "is_extracted": "true",
      "filetype": "application/pdf",
      "languages": [
        "eng"
      ],
      "page_number": 1,
      "filename": "Rule 57.pdf"
    }
  },
  {
    "type": "NarrativeText",
    "element_id": "268b39fb9dbd10ef85443a3de5725f97",
    "text": "RS 22, 2023, D1 Rule 57-1",
    "metadata": {
      "is_extracted": "true",
      "filetype": "application/pdf",
      "languages": [
        "eng"
      ],
      "page_number": 1,
      "filename": "Rule 57.pdf",
      "parent_id": "0a77ced28c402390c2835b9305b0b041"
    }
  },
  {
    "type": "UncategorizedText",
    "element_id": "5c771c50b6032942bf27a1fcd20e7e8b",
    "text": "(1) Any person desirous of making an application to the court for an order declaring another person (hereinafter referred to as ‘the patient’) to be of unsound mind and consequently incapable of managing his or her own affairs, and appointing a curator to the person or property of such patient shall in the first instance apply to the court for the appointment of a curator ad litem to such patient.",
    "metadata": {
      "filetype": "application/pdf",
      "languages": [
        "eng"
      ],
      "page_number": 1,
      "filename": "Rule 57.pdf",
      "parent_id": "0a77ced28c402390c2835b9305b0b041"
    }
  },
  {
    "type": "ListItem",
    "element_id": "993b7f6d795464ba8190f5bd81472d8f",
    "text": "(2) An application referred to in subrule (1) shall be brought ex parte and shall set forth fully —",
    "metadata": {
      "is_extracted": "true",
      "filetype": "application/pdf",
      "languages": [
        "eng"
      ],
      "page_number": 1,
      "filename": "Rule 57.pdf",
      "parent_id": "0a77ced28c402390c2835b9305b0b041"
    }
  },
  {
    "type": "ListItem",
    "element_id": "2837015fb00be182ad87c920a644207d",
    "text": "(a) the grounds upon which the applicant claims locus standi to make such application;",
    "metadata": {
      "is_extracted": "true",
      "filetype": "application/pdf",
      "languages": [
        "eng"
      ],
      "page_number": 1,
      "filename": "Rule 57.pdf",
      "parent_id": "0a77ced28c402390c2835b9305b0b041"
    }
  },
  {
    "type": "ListItem",
    "element_id": "a25cc425f45dd80bdd3e002f6798da1a",
    "text": "(b) the grounds upon which the court is alleged to have jurisdiction;",
    "metadata": {
      "is_extracted": "true",
      "filetype": "application/pdf",
      "languages": [
        "eng"
      ],
      "page_number": 1,
      "filename": "Rule 57.pdf",
      "parent_id": "0a77ced28c402390c2835b9305b0b041"
    }
  },
  {
    "type": "ListItem",
    "element_id": "300dd8ec0fe51ea5c440ca8b848dc112",
    "text": "(c) the patient’s age and sex, full particulars of the patient’s means, and information as to the patient’s general state of physical health;",
    "metadata": {
      "is_extracted": "true",
      "filetype": "application/pdf",
      "languages": [
        "eng"
      ],
      "page_number": 1,
      "filename": "Rule 57.pdf",
      "parent_id": "0a77ced28c402390c2835b9305b0b041"
    }
  },
  {
    "type": "ListItem",
    "element_id": "7a634b058f96451b3ac8818bad29d02f",
    "text": "(d) the relationship (if any) between the patient and the applicant, and the duration and intimacy of their association (if any);",
    "metadata": {
      "is_extracted": "true",
      "filetype": "application/pdf",
      "languages": [
        "eng"
      ],
      "page_number": 1,
      "filename": "Rule 57.pdf",
      "parent_id": "0a77ced28c402390c2835b9305b0b041"
    }
  },
  {
    "type": "ListItem",
    "element_id": "f6e565d4834d63cd3daa17cd04fbc685",
    "text": "(e) the facts and circumstances relied on to show that the patient is of unsound mind and incapable of managing his or her affairs;",
    "metadata": {
      "is_extracted": "true",
      "filetype": "application/pdf",
      "languages": [
        "eng"
      ],
      "page_number": 1,
      "filename": "Rule 57.pdf",
      "parent_id": "0a77ced28c402390c2835b9305b0b041"
    }
  },
  {
    "type": "ListItem",
    "element_id": "3b003c545886d6718cf7392c441559af",
    "text": "(f) the name, occupation and address of the respective persons suggested for appointment by the court as curator ad litem, and subsequently as curator to the patient’s person or property, and a statement that these persons have been approached and have intimated that, if appointed, they would be able and willing to act in these respective capacities.",
    "metadata": {
      "is_extracted": "true",
      "filetype": "application/pdf",
      "languages": [
        "eng"
      ],
      "page_number": 1,
      "filename": "Rule 57.pdf",
      "parent_id": "0a77ced28c402390c2835b9305b0b041"
    }
  },
  {
    "type": "ListItem",
    "element_id": "816ce87e336167c3596d1eb51bb83a1a",
    "text": "(3) The application shall, as far as possible, be supported by —",
    "metadata": {
      "is_extracted": "true",
      "filetype": "application/pdf",
      "languages": [
        "eng"
      ],
      "page_number": 1,
      "filename": "Rule 57.pdf",
      "parent_id": "0a77ced28c402390c2835b9305b0b041"
    }
  },
  {
    "type": "ListItem",
    "element_id": "513641ca938f0270c4b5822d96b51f46",
    "text": "(a) an affidavit by at least one person to whom the patient is well known and containing such facts and information as are within the deponent’s own knowledge concerning the patient’s mental condition. If such person is related to the patient, or has any personal interest in the terms of any order sought, full details of such relationship or interest, as the case may be, shall be set forth in the affidavit; and",
    "metadata": {
      "is_extracted": "true",
      "filetype": "application/pdf",
      "languages": [
        "eng"
      ],
      "page_number": 1,
      "filename": "Rule 57.pdf",
      "parent_id": "0a77ced28c402390c2835b9305b0b041"
    }
  },
  {
    "type": "ListItem",
    "element_id": "6d2462713b1a7fe4f42d2cc37a9b4282",
    "text": "(b) affidavits by at least two medical practitioners, one of whom shall, where practicable, be a psychiatrist or other medical practitioner with appropriate expertise, who have conducted recent examinations of the patient with a view to ascertaining and reporting upon the patient’s mental condition and stating all such facts as were observed by them at such examinations in regard to such condition, the opinions found by them in regard to the nature, extent and probable duration of any mental disorder or defect observed and their reasons for the same and whether the patient is in their opinion incapable of managing his or her affairs. Such medical practitioners shall, as far as possible, be persons unrelated to the patient, and without a personal interest in the terms of the order sought.",
    "metadata": {
      "is_extracted": "true",
      "filetype": "application/pdf",
      "languages": [
        "eng"
      ],
      "page_number": 1,
      "filename": "Rule 57.pdf",
      "parent_id": "0a77ced28c402390c2835b9305b0b041"
    }
  },
  {
    "type": "NarrativeText",
    "element_id": "0c90480a0a377781044570384f367fca",
    "text": "(4) Upon the hearing of the application referred to in subrule (1), the court may appoint the person suggested or any other suitable person as curator ad litem, or may dismiss the application or make such further or other order thereon as it deems fit and in particular on cause shown, and by reason of urgency, special circumstances or otherwise, dispense with any of the requirements of this rule.",
    "metadata": {
      "is_extracted": "true",
      "filetype": "application/pdf",
      "languages": [
        "eng"
      ],
      "page_number": 1,
      "filename": "Rule 57.pdf",
      "parent_id": "0a77ced28c402390c2835b9305b0b041"
    }
  },
  {
    "type": "NarrativeText",
    "element_id": "633606cfd76dfff2fea6658478afa1eb",
    "text": "RS 22, 2023, D1 Rule 57-2",
    "metadata": {
      "is_extracted": "true",
      "filetype": "application/pdf",
      "languages": [
        "eng"
      ],
      "page_number": 1,
      "filename": "Rule 57.pdf",
      "parent_id": "0a77ced28c402390c2835b9305b0b041"
    }
  },
  {
    "type": "ListItem",
    "element_id": "5d338d0c05271043d4bf2da88116a7af",
    "text": "(5) Upon appointment of the curator ad litem (who shall if practicable be an advocate, or failing such, an attorney), the curator shall without delay interview the patient, and shall also inform the patient of the purpose and nature of the application unless after consulting a medical practitioner referred to in paragraph (b) of subrule (3) the curator is satisfied that this would be detrimental to the patient’s health. The curator shall further make such inquiries as the case appears to require and shall thereafter prepare and file with the registrar, a report on the matter to the court, at the same time furnishing the applicant with a copy thereof. In the report, the curator shall set forth such further facts (if any) as the curator has ascertained in regard to the patient’s mental condition, means and circumstances and shall draw attention to any consideration which in the curator’s view might influence the court in regard to the terms of any order sought.",
    "metadata": {
      "is_extracted": "true",
      "filetype": "application/pdf",
      "languages": [
        "eng"
      ],
      "page_number": 1,
      "filename": "Rule 57.pdf",
      "parent_id": "0a77ced28c402390c2835b9305b0b041"
    }
  },
  {
    "type": "ListItem",
    "element_id": "e37e23eb435acd0fb22f44ebb331d454",
    "text": "(6) Upon receipt of the said report the applicant shall submit the report, together with copies of the documents referred to in subrules (2) and (3), to the Master of the High Court having jurisdiction, for consideration and report to the court.",
    "metadata": {
      "is_extracted": "true",
      "filetype": "application/pdf",
      "languages": [
        "eng"
      ],
      "page_number": 1,
      "filename": "Rule 57.pdf",
      "parent_id": "0a77ced28c402390c2835b9305b0b041"
    }
  },
  {
    "type": "ListItem",
    "element_id": "c7cc5303799d4a8f0f3abdc555b4f3ce",
    "text": "(7) In such report the Master shall, as far as possible, comment upon the patient’s means and general circumstances, and the suitability or otherwise of the person suggested for appointment as curator to the person or property of the patient, and the Master shall further make such recommendations as to the furnishing of security and rendering of accounts by, and the powers to be conferred on, such curator as the facts of the case appear to require. The curator ad litem shall be furnished with a copy of the said report.",
    "metadata": {
      "is_extracted": "true",
      "filetype": "application/pdf",
      "languages": [
        "eng"
      ],
      "page_number": 1,
      "filename": "Rule 57.pdf",
      "parent_id": "0a77ced28c402390c2835b9305b0b041"
    }
  },
  {
    "type": "ListItem",
    "element_id": "b258f161e0c7ff9d1c53ec2b8bd583e1",
    "text": "(8) After receipt of the report of the Master, the applicant may, on notice to the curator ad litem (who shall if considered advisable inform the patient thereof), place the matter on the roll for hearing on the same papers for an order declaring the patient to be of unsound mind and as such incapable of managing his or her affairs and for the appointment of the person suggested as curator to the person or property of the patient or to both.",
    "metadata": {
      "is_extracted": "true",
      "filetype": "application/pdf",
      "languages": [
        "eng"
      ],
      "page_number": 1,
      "filename": "Rule 57.pdf",
      "parent_id": "0a77ced28c402390c2835b9305b0b041"
    }
  },
  {
    "type": "ListItem",
    "element_id": "d671b44c6f2660a4ee6ebccdb8f28508",
    "text": "(9) At the hearing, the court may require the attendance of the applicant, the patient, and such other persons as it may think fit, to give evidence orally or to furnish information which the court may require.",
    "metadata": {
      "is_extracted": "true",
      "filetype": "application/pdf",
      "languages": [
        "eng"
      ],
      "page_number": 1,
      "filename": "Rule 57.pdf",
      "parent_id": "0a77ced28c402390c2835b9305b0b041"
    }
  },
  {
    "type": "UncategorizedText",
    "element_id": "385a066c561c8e419b8d388502afc763",
    "text": "(10) Upon consideration of the application, the reports of the curator ad litem and the Master and such further information or evidence (if any) as has been orally adduced, or otherwise, the court may direct service of the application on the patient or may declare the patient to be of unsound mind and incapable of managing his or her own affairs and may appoint a suitable person as curator to the patient’s person or property or both, on such terms as it deems fit, or it may dismiss the application or generally make such order (including an order that the costs of the proceedings be defrayed from the assets of the patient) as it deems fit.",
    "metadata": {
      "filetype": "application/pdf",
      "languages": [
        "eng"
      ],
      "page_number": 1,
      "filename": "Rule 57.pdf",
      "parent_id": "0a77ced28c402390c2835b9305b0b041"
    }
  },
  {
    "type": "ListItem",
    "element_id": "908c5657088af832694a76facef1b8c4",
    "text": "(11) Different persons may, subject to due compliance with the requirements of this rule in regard to each, be suggested and separately appointed as curator to the person and curator to the property of any person found to be of unsound mind and incapable of managing his or her own affairs.",
    "metadata": {
      "is_extracted": "true",
      "filetype": "application/pdf",
      "languages": [
        "eng"
      ],
      "page_number": 1,
      "filename": "Rule 57.pdf",
      "parent_id": "0a77ced28c402390c2835b9305b0b041"
    }
  },
  {
    "type": "ListItem",
    "element_id": "349c14aec1fb98115f8a281c55a461cf",
    "text": "(12) . . .",
    "metadata": {
      "is_extracted": "true",
      "filetype": "application/pdf",
      "languages": [
        "eng"
      ],
      "page_number": 1,
      "filename": "Rule 57.pdf",
      "parent_id": "0a77ced28c402390c2835b9305b0b041"
    }
  },
  {
    "type": "NarrativeText",
    "element_id": "40a24bdd56d7684626b1a62ed2517739",
    "text": "RS 22, 2023, D1 Rule 57-3",
    "metadata": {
      "is_extracted": "true",
      "filetype": "application/pdf",
      "languages": [
        "eng"
      ],
      "page_number": 1,
      "filename": "Rule 57.pdf",
      "parent_id": "0a77ced28c402390c2835b9305b0b041"
    }
  },
  {
    "type": "ListItem",
    "element_id": "40a6668a478c141e468af84bdf785e7d",
    "text": "(13) Save to the extent that the court may on application otherwise direct, the provisions of subrules (1) to (11) shall, with the necessary changes required by the context, apply to every application for the appointment of a curator bonis to any person on the ground that such person is by reason of some disability, mental or physical, incapable of managing his or her own affairs.",
    "metadata": {
      "is_extracted": "true",
      "filetype": "application/pdf",
      "languages": [
        "eng"
      ],
      "page_number": 1,
      "filename": "Rule 57.pdf",
      "parent_id": "0a77ced28c402390c2835b9305b0b041"
    }
  },
  {
    "type": "ListItem",
    "element_id": "1c9a2179c12526245f4bfdda0ca25c57",
    "text": "(14) Every person who has been declared by a court to be of unsound mind and incapable of managing his or her affairs, and to whose person or property a curator has been appointed, and who intends applying to court for a declaration that such person is no longer of unsound mind and incapable of managing his or her affairs or for release from curatorship, as the case may be, shall give 15 days’ notice of such application to such curator and to the Master.",
    "metadata": {
      "is_extracted": "true",
      "filetype": "application/pdf",
      "languages": [
        "eng"
      ],
      "page_number": 1,
      "filename": "Rule 57.pdf",
      "parent_id": "0a77ced28c402390c2835b9305b0b041"
    }
  },
  {
    "type": "ListItem",
    "element_id": "ac091f23ef1c30bd292ba2eb80f7112e",
    "text": "(15) Upon receipt of the notice referred to in subrule (14) and after due consideration of the application and the information available, the Master shall, without delay, report thereon to the court, and shall at the same time comment upon any aspect of the matter to which, in the Master’s view, the attention of the court should be drawn.",
    "metadata": {
      "is_extracted": "true",
      "filetype": "application/pdf",
      "languages": [
        "eng"
      ],
      "page_number": 1,
      "filename": "Rule 57.pdf",
      "parent_id": "0a77ced28c402390c2835b9305b0b041"
    }
  },
  {
    "type": "ListItem",
    "element_id": "7cdcc25ed73be52a608d728099a78c15",
    "text": "(16) . . .",
    "metadata": {
      "is_extracted": "true",
      "filetype": "application/pdf",
      "languages": [
        "eng"
      ],
      "page_number": 1,
      "filename": "Rule 57.pdf",
      "parent_id": "0a77ced28c402390c2835b9305b0b041"
    }
  },
  {
    "type": "ListItem",
    "element_id": "e551539ba5a4c313166322877ffcd623",
    "text": "(17) Upon the hearing of any application referred to in subrule (14) the court may declare the applicant as not being of unsound mind and as being capable of managing his or her affairs, order the applicant’s release from curatorship, or dismiss the application, or of its own accord appoint a curator ad litem to make any inquiries as it considers desirable and to report to it, or call for further evidence as it considers desirable and postpone the further hearing of the matter to permit the production of such report, affidavit or evidence, as the case may be, or postpone the matter indefinitely and make such order as to costs or otherwise as it deems fit.",
    "metadata": {
      "is_extracted": "true",
      "filetype": "application/pdf",
      "languages": [
        "eng"
      ],
      "page_number": 1,
      "filename": "Rule 57.pdf",
      "parent_id": "0a77ced28c402390c2835b9305b0b041"
    }
  },
  {
    "type": "NarrativeText",
    "element_id": "05aa83f50236a519a03708618d934e85",
    "text": "[Rule 57 amended by GN R1262 of 30 May 1991 and by GN R2410 of 30 September 1991, and substituted by GN R1603 of 17 December 2021.]",
    "metadata": {
      "is_extracted": "true",
      "filetype": "application/pdf",
      "languages": [
        "eng"
      ],
      "page_number": 1,
      "filename": "Rule 57.pdf",
      "parent_id": "0a77ced28c402390c2835b9305b0b041"
    }
  },
  {
    "type": "Title",
    "element_id": "608b2e57d883710ae560c7cb78289fb8",
    "text": "Commentary",
    "metadata": {
      "is_extracted": "true",
      "filetype": "application/pdf",
      "languages": [
        "eng"
      ],
      "page_number": 1,
      "filename": "Rule 57.pdf"
    }
  },
  {
    "type": "NarrativeText",
    "element_id": "17164140cffdbdc29ab7476fbd4d4804",
    "text": "General. This rule provides for the various steps that must be taken in an application for the appointment of a curator to the 1 person or property of a person.",
    "metadata": {
      "is_extracted": "true",
      "filetype": "application/pdf",
      "languages": [
        "eng"
      ],
      "page_number": 1,
      "filename": "Rule 57.pdf",
      "parent_id": "608b2e57d883710ae560c7cb78289fb8"
    }
  },
  {
    "type": "NarrativeText",
    "element_id": "8fcd15c89557c1561c0dd0d4dd52b5e6",
    "text": "The provisions of the rule are peremptory and, other than in the circumstances provided for in subrule (4), the failure to observe the provisions of the rule renders an application defective to the extent that such application cannot and should not 2 be entertained at all.",
    "metadata": {
      "is_extracted": "true",
      "filetype": "application/pdf",
      "languages": [
        "eng"
      ],
      "page_number": 1,
      "filename": "Rule 57.pdf",
      "parent_id": "608b2e57d883710ae560c7cb78289fb8"
    }
  },
  {
    "type": "NarrativeText",
    "element_id": "2e928de4b687c7391b58b91a11404878",
    "text": "Subrule (1): ‘Any person desirous of making an application.’ The appointment of a curator ad litem should be sought at 3 the earliest moment after it has become clear that the patient may be incapable of managing his own affairs.",
    "metadata": {
      "is_extracted": "true",
      "filetype": "application/pdf",
      "languages": [
        "eng"
      ],
      "page_number": 1,
      "filename": "Rule 57.pdf",
      "parent_id": "608b2e57d883710ae560c7cb78289fb8"
    }
  },
  {
    "type": "NarrativeText",
    "element_id": "621ef95e8c8e9b2e06fe7bc240920b74",
    "text": "‘Declaring another person . . . to be of unsound mind.’ Though this subrule speaks of an order declaring a person ‘to be of",
    "metadata": {
      "is_extracted": "true",
      "filetype": "application/pdf",
      "languages": [
        "eng"
      ],
      "page_number": 1,
      "filename": "Rule 57.pdf",
      "parent_id": "608b2e57d883710ae560c7cb78289fb8"
    }
  },
  {
    "type": "Footer",
    "element_id": "10c09c392606422524bb50dd2c9d044b",
    "text": "© 2025 Juta and Company (Pty) Ltd.",
    "metadata": {
      "is_extracted": "true",
      "filetype": "application/pdf",
      "languages": [
        "eng"
      ],
      "page_number": 1,
      "filename": "Rule 57.pdf"
    }
  },
  {
    "type": "Footer",
    "element_id": "ff6baae064255ea9811937c60c041638",
    "text": "Downloaded: Mon Feb 17 2025 12:10:40 GMT+0200 (South Africa Standard Time)",
    "metadata": {
      "is_extracted": "true",
      "filetype": "application/pdf",
      "languages": [
        "eng"
      ],
      "page_number": 1,
      "filename": "Rule 57.pdf"
    }
  },
  {
    "type": "PageBreak",
    "element_id": "2e6c343df2a53181f450b26a6d48de20",
    "text": "",
    "metadata": {
      "languages": [
        "eng"
      ],
      "filename": "Rule 57.pdf",
      "filetype": "application/pdf"
    }
  },
  {
    "type": "NarrativeText",
    "element_id": "0e331bd5b0cd046fb5951b8fc8785178",
    "text": "unsound mind’, in practice an order declaring the patient to be of unsound mind is not usually sought. This is recognized in subrule (13) in terms of",
    "metadata": {
      "is_extracted": "true",
      "filetype": "application/pdf",
      "languages": [
        "eng"
      ],
      "page_number": 2,
      "filename": "Rule 57.pdf"
    }
  },
  {
    "type": "NarrativeText",
    "element_id": "7e7a78d3c02bd3df0cec474423488040",
    "text": "RS 22, 2023, D1 Rule 57-4",
    "metadata": {
      "is_extracted": "true",
      "filetype": "application/pdf",
      "languages": [
        "eng"
      ],
      "page_number": 2,
      "filename": "Rule 57.pdf"
    }
  },
  {
    "type": "NarrativeText",
    "element_id": "aa617f595e01ee0be2f9fc17133beb36",
    "text": "which the provisions of the rule apply mutatis mutandis to applications for the appointment of a curator bonis to a person on 4 the ground that he is by reason of some disability, mental or physical, incapable of managing his own affairs.",
    "metadata": {
      "is_extracted": "true",
      "filetype": "application/pdf",
      "languages": [
        "eng"
      ],
      "page_number": 2,
      "filename": "Rule 57.pdf"
    }
  },
  {
    "type": "NarrativeText",
    "element_id": "38b626cff6f4ea342998b556f460f4d5",
    "text": "5 In Ex parte Van der Linde it was held that in an application under this rule there must be a prayer that the patient be declared of unsound mind and as such incapable of managing his own affairs. However, where the application for the appointment of a curator bonis is brought under subrule (13), a declaration of unsoundness of mind is not required.",
    "metadata": {
      "is_extracted": "true",
      "filetype": "application/pdf",
      "languages": [
        "eng"
      ],
      "page_number": 2,
      "filename": "Rule 57.pdf"
    }
  },
  {
    "type": "NarrativeText",
    "element_id": "919cc9377d5857406d8dce6fbaca01e2",
    "text": "It has been held that the preferable practice is that a patient who suffers from a mental disability resulting in the inability to manage all or some of his own affairs should be declared to be unable to do so. Such an order would protect the patient and those who interact with him and form the basis upon which the appointment of a curator bonis or a curator to the person is 6 justified in law.",
    "metadata": {
      "is_extracted": "true",
      "filetype": "application/pdf",
      "languages": [
        "eng"
      ],
      "page_number": 2,
      "filename": "Rule 57.pdf"
    }
  },
  {
    "type": "NarrativeText",
    "element_id": "9808f92c422c6e72e42cae58679867f6",
    "text": "‘Curator to the person.’ The appointment of a curator to the person involves serious encroachments upon the liberty of the 7 patient and should be made only when a real need for it has been shown. If the appointment of a curator bonis is sufficient 8 a curator to the person will not be appointed as well. A curator to the person will be appointed in a case where consent to perform an operation on the patient is necessary, but such an appointment may be limited to the sole function of deciding 9 whether or not the operation should be performed. A wife may be appointed curatrix to the person of her husband. 10",
    "metadata": {
      "is_extracted": "true",
      "filetype": "application/pdf",
      "languages": [
        "eng"
      ],
      "page_number": 2,
      "filename": "Rule 57.pdf"
    }
  },
  {
    "type": "NarrativeText",
    "element_id": "42f9e88eb36fb85a4f9c211e7b5652d5",
    "text": "‘Curator ad litem.’ A curator ad litem fulfils a very important function. It is, therefore, essential that the conditions set out in 11 subrules (1), (2) and (3) are met before such a curator is appointed.",
    "metadata": {
      "is_extracted": "true",
      "filetype": "application/pdf",
      "languages": [
        "eng"
      ],
      "page_number": 2,
      "filename": "Rule 57.pdf"
    }
  },
  {
    "type": "NarrativeText",
    "element_id": "b3e791e469a6ca1768092987ca2d8668",
    "text": "‘In the first instance apply . . . for the appointment of a curator ad litem to such patient.’ It is customary to include a prayer catering for the situation contemplated in subrule (8) i e to the effect that the matter may again be placed on the roll for hearing on the same papers for an order declaring the patient to be of unsound mind, etc and, accordingly, to postpone the proceedings sine die for that purpose.",
    "metadata": {
      "is_extracted": "true",
      "filetype": "application/pdf",
      "languages": [
        "eng"
      ],
      "page_number": 2,
      "filename": "Rule 57.pdf"
    }
  },
  {
    "type": "NarrativeText",
    "element_id": "d45f214c60aa9a0b6f609cd3e82a644e",
    "text": "Subrule (2): ‘Shall be brought ex parte.’ It is submitted that where the costs of the application for the appointment of a curator bonis are to be claimed as part of the award in an action for damages for bodily injuries which have necessitated the 12 appointment of a curator bonis to the injured party, notice of the application for the appointment of a curator bonis should be served on the insurance company concerned.",
    "metadata": {
      "is_extracted": "true",
      "filetype": "application/pdf",
      "languages": [
        "eng"
      ],
      "page_number": 2,
      "filename": "Rule 57.pdf"
    }
  },
  {
    "type": "NarrativeText",
    "element_id": "b47367381854baeec9f9fdfdce0574bc",
    "text": "RS 22, 2023, D1 Rule 57-5",
    "metadata": {
      "is_extracted": "true",
      "filetype": "application/pdf",
      "languages": [
        "eng"
      ],
      "page_number": 2,
      "filename": "Rule 57.pdf"
    }
  },
  {
    "type": "NarrativeText",
    "element_id": "efb70fa4bb09dd689f0f9840df69141a",
    "text": "Subrule (2)(a): ‘The applicant claims locus standi.’ The application is usually brought by one of the patient’s next-of-kin, but where the patient has no relatives in the Republic, the application may be brought by any person with a sufficient interest 13 14 in the person of the patient, such as a friend or even a partner or business associate. In Ex parte Knight a curator bonis was appointed on the application of an assistant welfare officer in the then Department of Social Welfare.",
    "metadata": {
      "is_extracted": "true",
      "filetype": "application/pdf",
      "languages": [
        "eng"
      ],
      "page_number": 2,
      "filename": "Rule 57.pdf"
    }
  },
  {
    "type": "NarrativeText",
    "element_id": "162de5aa148a3591648f346190a8482f",
    "text": "Subrule (2)(b): ‘The court is alleged to have jurisdiction.’ In Ex parte Berry: In re Berry 15 it was held, on a comprehensive review of the authorities, that any division of the Supreme Court (i e the High Court) has jurisdiction to declare incapable of managing his affairs and place under curatorship any person who is domiciled within its area of jurisdiction or whose assets are within such area, notwithstanding that he himself is not within the area. This decision was confirmed in Ex 16 parte De Villiers, in which it was held that s 60(1) of the (now repealed) Mental Health Act 18 of 1973 specifically preserved such common-law jurisdiction as a court might have to declare a person to be of unsound mind and to appoint a curator bonis.",
    "metadata": {
      "is_extracted": "true",
      "filetype": "application/pdf",
      "languages": [
        "eng"
      ],
      "page_number": 2,
      "filename": "Rule 57.pdf"
    }
  },
  {
    "type": "NarrativeText",
    "element_id": "34ed8e51b4dfb4b00e869cff912ef586",
    "text": "Subrule (2)(c): ‘Information as to his general state of physical health.’ It is submitted that such information must fall within the personal knowledge of the deponent to the founding affidavit. If not, supporting affidavits to prove the patient’s general state of physical health must be filed. In addition, the affidavits by the medical practitioners contemplated in subrule (3)(b) must, as far as possible, be filed in support of the application.",
    "metadata": {
      "is_extracted": "true",
      "filetype": "application/pdf",
      "languages": [
        "eng"
      ],
      "page_number": 2,
      "filename": "Rule 57.pdf"
    }
  },
  {
    "type": "NarrativeText",
    "element_id": "d36982ebda7ec17e6a6b7a526eb90b0e",
    "text": "Subrule (2)(e): ‘To show that the patient is of unsound mind and incapable of managing his or her affairs.’ It is submitted that such facts and circumstances must fall within the personal knowledge of the deponent to the founding affidavit. If not, supporting affidavits to prove the patient’s mental condition must be filed. In addition, the affidavits by the medical practitioners contemplated in subrule (3)(b) must, as far as possible, be filed in support of the application.",
    "metadata": {
      "is_extracted": "true",
      "filetype": "application/pdf",
      "languages": [
        "eng"
      ],
      "page_number": 2,
      "filename": "Rule 57.pdf"
    }
  },
  {
    "type": "NarrativeText",
    "element_id": "31b74451bc1e5257e4837d67668b7bc7",
    "text": "Subrule (2)(f): ‘Statement that . . . they would be able and willing to act.’ Consents to act as curator ad litem and curator bonis if appointed by the court should be annexed to the application.",
    "metadata": {
      "is_extracted": "true",
      "filetype": "application/pdf",
      "languages": [
        "eng"
      ],
      "page_number": 2,
      "filename": "Rule 57.pdf"
    }
  },
  {
    "type": "NarrativeText",
    "element_id": "8232961069298b54c95f29f025087280",
    "text": "A curator ad litem must be of sufficient experience, proven expertise and good standing to ensure that the interests of the 17 patient are best served. It is important that the curator ad litem is professionally independent. See further the notes to subrule (5) s v ‘Who shall if practicable be an advocate’ below.",
    "metadata": {
      "is_extracted": "true",
      "filetype": "application/pdf",
      "languages": [
        "eng"
      ],
      "page_number": 2,
      "filename": "Rule 57.pdf"
    }
  },
  {
    "type": "NarrativeText",
    "element_id": "a5fc88b533be7e72b7dc2f16500c32bb",
    "text": "Subrule (3): ‘As far as possible, be supported.’ It is not an absolute requirement that the application be supported by the affidavits contemplated in this subrule. The subrule requires that the application shall ‘as far as possible’ be supported by the affidavits. It is submitted that all reasonable attempts should be made to obtain the affidavits and that in the absence of obtaining them, the attempts made should be disclosed to the court in the founding affidavit or a supporting affidavit to the application.",
    "metadata": {
      "is_extracted": "true",
      "filetype": "application/pdf",
      "languages": [
        "eng"
      ],
      "page_number": 2,
      "filename": "Rule 57.pdf"
    }
  },
  {
    "type": "NarrativeText",
    "element_id": "cf428b8a2735675291cef773be63be45",
    "text": "RS 22, 2023, D1 Rule 57-6",
    "metadata": {
      "is_extracted": "true",
      "filetype": "application/pdf",
      "languages": [
        "eng"
      ],
      "page_number": 2,
      "filename": "Rule 57.pdf"
    }
  },
  {
    "type": "NarrativeText",
    "element_id": "9db1cc99b77420aa7fe8aeeee4e2fd19",
    "text": "Subrule (4): ‘May appoint . . . as curator ad litem.’ It has often been held that the court will not dispense with the 18 appointment of a curator ad litem even if it is clear that a curator bonis will have to be appointed. The present rule, it is submitted, contemplates that as a normal rule a curator ad litem will be appointed though the court has power, under this subrule, to dispense with such an appointment on the grounds of urgency, other special circumstances or otherwise. 19 The appointment of a curator ad litem may be dispensed with if there is reason to believe that the person concerned understands 20 the nature or effect of the proceedings. The appointment of a curator ad litem is usually dispensed with in applications for the appointment of a curator bonis to a prodigal, there being in such cases no declaration as to unsoundness of mind. 21",
    "metadata": {
      "is_extracted": "true",
      "filetype": "application/pdf",
      "languages": [
        "eng"
      ],
      "page_number": 2,
      "filename": "Rule 57.pdf"
    }
  },
  {
    "type": "NarrativeText",
    "element_id": "b3fb4901acc31acba6ab2477b98de023",
    "text": "As to the extent to which lack of finance will be regarded as a special circumstance, see Ex parte Griesel. that the patient consents is insufficient reason for dispensing with the appointment of a curator ad litem. 23 22 The mere fact",
    "metadata": {
      "is_extracted": "true",
      "filetype": "application/pdf",
      "languages": [
        "eng"
      ],
      "page_number": 2,
      "filename": "Rule 57.pdf"
    }
  },
  {
    "type": "NarrativeText",
    "element_id": "705e1c845c7ffe04a90985ed013c2442",
    "text": "‘By reason of urgency, special circumstances or otherwise.’ The court may as a matter of urgency appoint a curator for a 24 or to assist a specific purpose, for example, to decide whether or not an operation on the patient should be performed 25 person at a meeting.",
    "metadata": {
      "is_extracted": "true",
      "filetype": "application/pdf",
      "languages": [
        "eng"
      ],
      "page_number": 2,
      "filename": "Rule 57.pdf"
    }
  },
  {
    "type": "NarrativeText",
    "element_id": "ceb99e5b7f166a8ed86fd235c02a9d65",
    "text": "‘Dispense with any of the requirements of this rule.’ The court has a wide discretion to dispense with the requirements of",
    "metadata": {
      "is_extracted": "true",
      "filetype": "application/pdf",
      "languages": [
        "eng"
      ],
      "page_number": 2,
      "filename": "Rule 57.pdf"
    }
  },
  {
    "type": "Footer",
    "element_id": "e28ac7e560f0f1658874abc7d5f2654b",
    "text": "26 © 2025 Juta and Company (Pty) Ltd.",
    "metadata": {
      "is_extracted": "true",
      "filetype": "application/pdf",
      "languages": [
        "eng"
      ],
      "page_number": 2,
      "filename": "Rule 57.pdf"
    }
  },
  {
    "type": "Footer",
    "element_id": "94215437ba915db270aee55937ce2f52",
    "text": "Downloaded: Mon Feb 17 2025 12:10:40 GMT+0200 (South Africa Standard Time)",
    "metadata": {
      "is_extracted": "true",
      "filetype": "application/pdf",
      "languages": [
        "eng"
      ],
      "page_number": 2,
      "filename": "Rule 57.pdf"
    }
  },
  {
    "type": "PageBreak",
    "element_id": "3a9bd49f191ad85ccf38e4ec1ef9d571",
    "text": "",
    "metadata": {
      "languages": [
        "eng"
      ],
      "filename": "Rule 57.pdf",
      "filetype": "application/pdf"
    }
  },
  {
    "type": "Header",
    "element_id": "5d14aa67761938ca1f1a9ef1d459554f",
    "text": "the rule. 26",
    "metadata": {
      "is_extracted": "true",
      "filetype": "application/pdf",
      "languages": [
        "eng"
      ],
      "page_number": 3,
      "filename": "Rule 57.pdf"
    }
  },
  {
    "type": "NarrativeText",
    "element_id": "81de15367953f6a4037ef81356997e34",
    "text": "Subrule (5): ‘Who shall if practicable be an advocate.’ It has been held that ‘doenlik’ (‘practicable’) in this context means 27 ‘prakties uitvoerbaar’. If the patient lives far from the seat of the court, the saving in travelling expenses achieved by the appointment of a local attorney as curator ad litem is cancelled out by the fact that the curator ad litem might have to 28 The appointment of an advocate as curator ad litem has been termed ‘ ’n attend court when the application is heard. 29 gesonde praktyk’; indeed in some, if not most cases, it is preferable that the curator ad litem be someone completely 30 independent and outside the range of local influence.",
    "metadata": {
      "is_extracted": "true",
      "filetype": "application/pdf",
      "languages": [
        "eng"
      ],
      "page_number": 3,
      "filename": "Rule 57.pdf",
      "parent_id": "5d14aa67761938ca1f1a9ef1d459554f"
    }
  },
  {
    "type": "NarrativeText",
    "element_id": "0b4e404022e8c60e93fbde30ee6556d8",
    "text": "RS 22, 2023, D1 Rule 57-7",
    "metadata": {
      "is_extracted": "true",
      "filetype": "application/pdf",
      "languages": [
        "eng"
      ],
      "page_number": 3,
      "filename": "Rule 57.pdf",
      "parent_id": "5d14aa67761938ca1f1a9ef1d459554f"
    }
  },
  {
    "type": "NarrativeText",
    "element_id": "5e9f58256fc33c624ba3ed4bc567c77c",
    "text": "In Ex parte Mallach 31 Mason J stated:",
    "metadata": {
      "is_extracted": "true",
      "filetype": "application/pdf",
      "languages": [
        "eng"
      ],
      "page_number": 3,
      "filename": "Rule 57.pdf",
      "parent_id": "5d14aa67761938ca1f1a9ef1d459554f"
    }
  },
  {
    "type": "UncategorizedText",
    "element_id": "309b1a7aa4c5ffe42fba92512783c87c",
    "text": "‘.. .in ordinary applications for the appointment of a curator ad litem to the property of any person found to be of unsound mind the Court always requires that some independent person acting as curator ad litem on behalf of the person supposed to be insane, should independently investigate the matter.”",
    "metadata": {
      "filetype": "application/pdf",
      "languages": [
        "eng"
      ],
      "page_number": 3,
      "filename": "Rule 57.pdf",
      "parent_id": "5d14aa67761938ca1f1a9ef1d459554f"
    }
  },
  {
    "type": "UncategorizedText",
    "element_id": "72d7343104ed673d2b561cf78b3a98b1",
    "text": "In Modiba: In re Ruca v Road Accident Fund 32 Bertelsmann J stated:",
    "metadata": {
      "filetype": "application/pdf",
      "languages": [
        "eng"
      ],
      "page_number": 3,
      "filename": "Rule 57.pdf",
      "parent_id": "5d14aa67761938ca1f1a9ef1d459554f"
    }
  },
  {
    "type": "NarrativeText",
    "element_id": "6de3c35e0253b2bc325856f3f95ff455",
    "text": "‘It follows that a curator ad litem must be (ordinarily) an advocate of sufficient experience, proven expertise and good standing to ensure that the patient receives optimal forensic advice and service; see Soller NO v G & Another 2003 (5) SA 430 (W) at 436B–437A. Advocates are — as members of a referral profession practising individually — generally regarded as being professionally independent as they are not beholden to clients other than in respect of the particular brief that has been entrusted to them. One non-negotiable quality of an advocate (or attorney) acting as curator must be indisputable independence to ensure the integrity of the professional service that must be rendered to the patient.’",
    "metadata": {
      "is_extracted": "true",
      "filetype": "application/pdf",
      "languages": [
        "eng"
      ],
      "page_number": 3,
      "filename": "Rule 57.pdf",
      "parent_id": "5d14aa67761938ca1f1a9ef1d459554f"
    }
  },
  {
    "type": "NarrativeText",
    "element_id": "713bfec161072c041555a23cf4be261a",
    "text": "‘Or failing such, an attorney.’ The curator ad litem should preferably be a person who is directly answerable to the 33 court. In special circumstances a magistrate may be appointed; but this power will be sparingly exercised and the relevant 34 facts which might justify such an appointment must be fully stated in the application.",
    "metadata": {
      "is_extracted": "true",
      "filetype": "application/pdf",
      "languages": [
        "eng"
      ],
      "page_number": 3,
      "filename": "Rule 57.pdf",
      "parent_id": "5d14aa67761938ca1f1a9ef1d459554f"
    }
  },
  {
    "type": "NarrativeText",
    "element_id": "2cd08b45f9b9fb3e47662255e8e4f671",
    "text": "‘The curator . . . shall.’ The position of a curator ad litem is one of considerable responsibility and the court is greatly 35 It is the duty dependent upon the proper exercise of a curator’s duties in arriving at a just decision in any particular case. 36 of the curator ad litem, by making such enquiries as he deems necessary, to see that the existence and extent of the patient’s mental illness are properly investigated, and to ensure that the proprietary and other interests of the patient are 37 adequately protected by the terms of the order made by the court.",
    "metadata": {
      "is_extracted": "true",
      "filetype": "application/pdf",
      "languages": [
        "eng"
      ],
      "page_number": 3,
      "filename": "Rule 57.pdf",
      "parent_id": "5d14aa67761938ca1f1a9ef1d459554f"
    }
  },
  {
    "type": "NarrativeText",
    "element_id": "e05f5e5fb690326def0105e6f981f8c7",
    "text": "The curator ad litem is entitled to receive the fullest information from the applicant regarding any reasonable enquiry he may raise: in practice the applicant’s attorneys should at once place before the curator ad litem all the information at their 38 disposal. In exceptional circumstances application may be made for the appointment of an independent attorney or 39 advocate to assist the curator ad litem.",
    "metadata": {
      "is_extracted": "true",
      "filetype": "application/pdf",
      "languages": [
        "eng"
      ],
      "page_number": 3,
      "filename": "Rule 57.pdf",
      "parent_id": "5d14aa67761938ca1f1a9ef1d459554f"
    }
  },
  {
    "type": "NarrativeText",
    "element_id": "00292db18d3c504b0d5714e0d2056e24",
    "text": "‘Prepare and file . . . a report.’ This subrule requires the curator ad litem to set forth in his report such further facts as he may have ascertained regarding the patient’s mental condition, means and circumstances, and to draw attention to any consideration which might influence the court in regard to the order sought. Though a curator ad litem may in certain",
    "metadata": {
      "is_extracted": "true",
      "filetype": "application/pdf",
      "languages": [
        "eng"
      ],
      "page_number": 3,
      "filename": "Rule 57.pdf",
      "parent_id": "5d14aa67761938ca1f1a9ef1d459554f"
    }
  },
  {
    "type": "NarrativeText",
    "element_id": "5de119e6294ead9ca2fb568888c010ab",
    "text": "RS 22, 2023, D1 Rule 57-8",
    "metadata": {
      "is_extracted": "true",
      "filetype": "application/pdf",
      "languages": [
        "eng"
      ],
      "page_number": 3,
      "filename": "Rule 57.pdf",
      "parent_id": "5d14aa67761938ca1f1a9ef1d459554f"
    }
  },
  {
    "type": "NarrativeText",
    "element_id": "1ee99e9fcd254c8ae18f24b8a4d72364",
    "text": "40 circumstances function rather as an amicus curiae, his primary function in the present context is to ensure that the 41 proprietary and other interests of the patient are adequately protected.",
    "metadata": {
      "is_extracted": "true",
      "filetype": "application/pdf",
      "languages": [
        "eng"
      ],
      "page_number": 3,
      "filename": "Rule 57.pdf",
      "parent_id": "5d14aa67761938ca1f1a9ef1d459554f"
    }
  },
  {
    "type": "NarrativeText",
    "element_id": "1b34a326bf6cf760b0c780fc0baa6d97",
    "text": "Subrule (6): ‘The applicant shall submit . . . to the Master of the High Court having jurisdiction.’ The jurisdiction of the Master is determined by the Administration of Estates Act 66 of 1965 and is quite distinguishable from the jurisdiction of the 42 court, which, in general, is determined by the Superior Courts Act 10 of 2013 and the common law. Under s 4(2)–(4) of the Administration of Estates Act 66 of 1965 the jurisdiction of a Master in respect of property belonging to a person under curatorship or to be placed under curatorship lies, for purposes of this subrule and subrule (7) —",
    "metadata": {
      "is_extracted": "true",
      "filetype": "application/pdf",
      "languages": [
        "eng"
      ],
      "page_number": 3,
      "filename": "Rule 57.pdf",
      "parent_id": "5d14aa67761938ca1f1a9ef1d459554f"
    }
  },
  {
    "type": "ListItem",
    "element_id": "53e61320e8460b794c0068937a1f026f",
    "text": "(a) in the case of any such person who is ordinarily resident within the area of jurisdiction of a division of a High Court, with the Master appointed in respect of that area;",
    "metadata": {
      "is_extracted": "true",
      "filetype": "application/pdf",
      "languages": [
        "eng"
      ],
      "page_number": 3,
      "filename": "Rule 57.pdf",
      "parent_id": "5d14aa67761938ca1f1a9ef1d459554f"
    }
  },
  {
    "type": "ListItem",
    "element_id": "fc79f687d107a2c3288234328e039b77",
    "text": "(b) in the case of any such person who is not so resident, with the Master appointed in respect of any such area in which is situate the greater or greatest portion of the property of that person.",
    "metadata": {
      "is_extracted": "true",
      "filetype": "application/pdf",
      "languages": [
        "eng"
      ],
      "page_number": 3,
      "filename": "Rule 57.pdf",
      "parent_id": "5d14aa67761938ca1f1a9ef1d459554f"
    }
  },
  {
    "type": "NarrativeText",
    "element_id": "a492136cf50bc346255c66781eebe94d",
    "text": "It has been held that the provisions of s 4(2)(b) of the Administration of Estates Act 66 of 1965 apply only in respect of the property of a person under curatorship or to be placed under curatorship if such person is not ordinarily resident within the 43 area of jurisdiction of a High Court, and that the provisions apply in respect of the local property of an affected person who 44 is not ordinarily resident in the Republic, but who owns property that is held or situated here. The provisions of s 4(2)(b) of the Administration of Estates Act 66 of 1965 might also apply in respect of a person who has no fixed place of residence in the Republic, but constantly moves about the country staying at different places from time to time, consequently not being 45 ‘ordinarily resident’ anywhere in the country.",
    "metadata": {
      "is_extracted": "true",
      "filetype": "application/pdf",
      "languages": [
        "eng"
      ],
      "page_number": 3,
      "filename": "Rule 57.pdf",
      "parent_id": "5d14aa67761938ca1f1a9ef1d459554f"
    }
  },
  {
    "type": "NarrativeText",
    "element_id": "a489c5ba90edfd2a13ad25b4476810bd",
    "text": "Subrule (7): ‘In such report the Master shall.’ The provisions of this subrule are peremptory. 46",
    "metadata": {
      "is_extracted": "true",
      "filetype": "application/pdf",
      "languages": [
        "eng"
      ],
      "page_number": 3,
      "filename": "Rule 57.pdf",
      "parent_id": "5d14aa67761938ca1f1a9ef1d459554f"
    }
  },
  {
    "type": "NarrativeText",
    "element_id": "7a6add807df6ee27b2c2a3186172c87f",
    "text": "‘The furnishing of security.’ The court has the power to grant exemption to a curator bonis from furnishing security and will 47 exercise such discretion when exceptional circumstances exist.",
    "metadata": {
      "is_extracted": "true",
      "filetype": "application/pdf",
      "languages": [
        "eng"
      ],
      "page_number": 3,
      "filename": "Rule 57.pdf",
      "parent_id": "5d14aa67761938ca1f1a9ef1d459554f"
    }
  },
  {
    "type": "NarrativeText",
    "element_id": "69737993d3643a4f8fb6ca5f11fcacfb",
    "text": "Subrule (9): ‘At the hearing, the court may require the attendance.’ The curator ad litem ordinarily appears at the 48 hearing.",
    "metadata": {
      "is_extracted": "true",
      "filetype": "application/pdf",
      "languages": [
        "eng"
      ],
      "page_number": 3,
      "filename": "Rule 57.pdf",
      "parent_id": "5d14aa67761938ca1f1a9ef1d459554f"
    }
  },
  {
    "type": "NarrativeText",
    "element_id": "6053a131ffee7c100e887809ecdf0391",
    "text": "‘To give evidence orally or to furnish information which the court may require.’ Formerly all the evidence, including the 49 medical evidence, was placed before the court viva voce. Today",
    "metadata": {
      "is_extracted": "true",
      "filetype": "application/pdf",
      "languages": [
        "eng"
      ],
      "page_number": 3,
      "filename": "Rule 57.pdf",
      "parent_id": "5d14aa67761938ca1f1a9ef1d459554f"
    }
  },
  {
    "type": "NarrativeText",
    "element_id": "0fa687ed0ba52f11761c0e02b9adec07",
    "text": "RS 22, 2023, D1 Rule 57-9",
    "metadata": {
      "is_extracted": "true",
      "filetype": "application/pdf",
      "languages": [
        "eng"
      ],
      "page_number": 3,
      "filename": "Rule 57.pdf",
      "parent_id": "5d14aa67761938ca1f1a9ef1d459554f"
    }
  },
  {
    "type": "NarrativeText",
    "element_id": "456cedbb6bb45440b90495bb778ff283",
    "text": "the evidence is usually placed before the court by way of affidavit, but it is submitted that the court may either of its own motion or at the request of the curator ad litem or any other party direct that viva voce evidence should be produced.",
    "metadata": {
      "is_extracted": "true",
      "filetype": "application/pdf",
      "languages": [
        "eng"
      ],
      "page_number": 3,
      "filename": "Rule 57.pdf",
      "parent_id": "5d14aa67761938ca1f1a9ef1d459554f"
    }
  },
  {
    "type": "NarrativeText",
    "element_id": "1a086e1fb369c6300bfd979b0f038aaf",
    "text": "Subrule (10): ‘Declare the patient to be of unsound mind and incapable of managing his or her own affairs.’ See the notes to subrule (1) s v ‘Declaring another person . . . to be of unsound mind’ above.",
    "metadata": {
      "is_extracted": "true",
      "filetype": "application/pdf",
      "languages": [
        "eng"
      ],
      "page_number": 3,
      "filename": "Rule 57.pdf",
      "parent_id": "5d14aa67761938ca1f1a9ef1d459554f"
    }
  },
  {
    "type": "NarrativeText",
    "element_id": "90c1d968be3bb630a6560d1c99027bb2",
    "text": "If the application for the appointment of a curator bonis is brought under subrule (13), a declaration of unsoundness of mind is not required.",
    "metadata": {
      "is_extracted": "true",
      "filetype": "application/pdf",
      "languages": [
        "eng"
      ],
      "page_number": 3,
      "filename": "Rule 57.pdf",
      "parent_id": "5d14aa67761938ca1f1a9ef1d459554f"
    }
  },
  {
    "type": "NarrativeText",
    "element_id": "715b1bf4f1bba42fc083f3de6796652c",
    "text": "‘Appoint a suitable person as curator to the patient’s person or property or both.’ As to the appointment of a curator to the person, see the notes to subrule (1) s v ‘Curator to the person’ above. A court will not appoint a curator bonis until it is absolutely satisfied that the patient has to be protected against loss which would be caused because the patient is unable to",
    "metadata": {
      "is_extracted": "true",
      "filetype": "application/pdf",
      "languages": [
        "eng"
      ],
      "page_number": 3,
      "filename": "Rule 57.pdf",
      "parent_id": "5d14aa67761938ca1f1a9ef1d459554f"
    }
  },
  {
    "type": "Footer",
    "element_id": "f5c9a792580ddbcc1adc9a523009db2b",
    "text": "© 2025 Juta and Company (Pty) Ltd.",
    "metadata": {
      "is_extracted": "true",
      "filetype": "application/pdf",
      "languages": [
        "eng"
      ],
      "page_number": 3,
      "filename": "Rule 57.pdf"
    }
  },
  {
    "type": "UncategorizedText",
    "element_id": "f431520bdf3e6160c9e529178cb27607",
    "text": "50",
    "metadata": {
      "is_extracted": "true",
      "filetype": "application/pdf",
      "languages": [
        "eng"
      ],
      "page_number": 3,
      "filename": "Rule 57.pdf"
    }
  },
  {
    "type": "Footer",
    "element_id": "67c9219eae4fd2535c8a021c41fffe07",
    "text": "Downloaded: Mon Feb 17 2025 12:10:40 GMT+0200 (South Africa Standard Time)",
    "metadata": {
      "is_extracted": "true",
      "filetype": "application/pdf",
      "languages": [
        "eng"
      ],
      "page_number": 3,
      "filename": "Rule 57.pdf"
    }
  },
  {
    "type": "PageBreak",
    "element_id": "2e6c343df2a53181f450b26a6d48de20",
    "text": "",
    "metadata": {
      "languages": [
        "eng"
      ],
      "filename": "Rule 57.pdf",
      "filetype": "application/pdf"
    }
  },
  {
    "type": "NarrativeText",
    "element_id": "9a1eaa3bf5818d1c3501c0c6137343b6",
    "text": "manage his affairs. 50",
    "metadata": {
      "is_extracted": "true",
      "filetype": "application/pdf",
      "languages": [
        "eng"
      ],
      "page_number": 4,
      "filename": "Rule 57.pdf"
    }
  },
  {
    "type": "NarrativeText",
    "element_id": "5dbafef79820a402da8e70e658242c11",
    "text": "‘On such terms as it deems fit.’ While the Administration of Estates Act 66 of 1965 to some extent defines the powers and duties of all curators, it is desirable that any order of court appointing a curator should specify the powers conferred upon the 51 52 53 the orders of court in Ex parte Van Hasselt; curator. Ex parte Du Toit: In re Curatorship Estate See, for example, 55 57 54 56 Reyneke NO v Mutual & Federal Insurance Co Ltd; Meyer v Thompson NO; Schwab; Ex parte Hulett; Ex parte 58 and see the amplification to the original order granted in Ex parte Wagner NO: In re De Bie. Ewing NO: In re Sheridan; 59",
    "metadata": {
      "is_extracted": "true",
      "filetype": "application/pdf",
      "languages": [
        "eng"
      ],
      "page_number": 4,
      "filename": "Rule 57.pdf"
    }
  },
  {
    "type": "NarrativeText",
    "element_id": "83f371a50460436cc1265899448c75be",
    "text": "It is advisable to obtain the court’s sanction for any remuneration that may be payable to the curator. Remuneration is generally allowed where the estate is complex and the curator is a professional man or a representative of a bank or trust company. It is not usually — although it may be — claimed where the curator is a relative of the patient.",
    "metadata": {
      "is_extracted": "true",
      "filetype": "application/pdf",
      "languages": [
        "eng"
      ],
      "page_number": 4,
      "filename": "Rule 57.pdf"
    }
  },
  {
    "type": "NarrativeText",
    "element_id": "e1153b01442f18c4f6a26057c71c4e24",
    "text": "As to the furnishing of security by a curator bonis, see the notes to subrule (7) s v ‘The furnishing of security’ above.",
    "metadata": {
      "is_extracted": "true",
      "filetype": "application/pdf",
      "languages": [
        "eng"
      ],
      "page_number": 4,
      "filename": "Rule 57.pdf"
    }
  },
  {
    "type": "NarrativeText",
    "element_id": "f09db4527bb32a3ffca772e7a09c6f8e",
    "text": "‘Dismiss the application.’ While each case must be decided on its own facts, it can be said that in general the court will not 60 appoint a curator where the person concerned is compos mentis and actively opposes any such appointment.",
    "metadata": {
      "is_extracted": "true",
      "filetype": "application/pdf",
      "languages": [
        "eng"
      ],
      "page_number": 4,
      "filename": "Rule 57.pdf"
    }
  },
  {
    "type": "NarrativeText",
    "element_id": "ec7e47cd8e136a9390eac74129e9fc5e",
    "text": "‘That the costs of the proceedings be defrayed from the assets of the patient.’ The usual order is that the costs of the application, as between attorney and client, including the costs of the application for the appointment and the fees of the 61 curator ad litem, be paid out of the estate of the patient. Where the court dismisses an application it will apply the usual rule",
    "metadata": {
      "is_extracted": "true",
      "filetype": "application/pdf",
      "languages": [
        "eng"
      ],
      "page_number": 4,
      "filename": "Rule 57.pdf"
    }
  },
  {
    "type": "NarrativeText",
    "element_id": "21c48842097433bca3dad8103207ed3c",
    "text": "RS 22, 2023, D1 Rule 57-10",
    "metadata": {
      "is_extracted": "true",
      "filetype": "application/pdf",
      "languages": [
        "eng"
      ],
      "page_number": 4,
      "filename": "Rule 57.pdf"
    }
  },
  {
    "type": "NarrativeText",
    "element_id": "f5cb839780ddf253882adb9107f47ebc",
    "text": "and do so with costs, which costs are to include the costs of the curator ad litem. 62",
    "metadata": {
      "is_extracted": "true",
      "filetype": "application/pdf",
      "languages": [
        "eng"
      ],
      "page_number": 4,
      "filename": "Rule 57.pdf"
    }
  },
  {
    "type": "NarrativeText",
    "element_id": "7415a29e9493bdaa48376b304a4d8fe6",
    "text": "In an action for damages for bodily injuries which have necessitated the appointment of a curator bonis to the injured party, the costs of the application for the appointment of a curator bonis are quantified and included in the total award of 63 damages.",
    "metadata": {
      "is_extracted": "true",
      "filetype": "application/pdf",
      "languages": [
        "eng"
      ],
      "page_number": 4,
      "filename": "Rule 57.pdf"
    }
  },
  {
    "type": "NarrativeText",
    "element_id": "d577a98247020bfea75fd0f3e7557907",
    "text": "Subrule (13): ‘By reason of some disability, mental or physical, incapable of managing his or her own affairs.’ In terms of this subrule a curator bonis may be appointed to a person who is incapable of managing his own affairs by reason of 64 some mental or physical disability. In an application for the appointment of a curator bonis brought under the subrule, the court need not, as is required by subrule (10), declare the patient to be of unsound mind.",
    "metadata": {
      "is_extracted": "true",
      "filetype": "application/pdf",
      "languages": [
        "eng"
      ],
      "page_number": 4,
      "filename": "Rule 57.pdf"
    }
  },
  {
    "type": "NarrativeText",
    "element_id": "478b8849d82c007797079b50d57f67d6",
    "text": "See further the notes to subrule (1) s v ‘Declaring another person . . . to be of unsound mind’ above.",
    "metadata": {
      "is_extracted": "true",
      "filetype": "application/pdf",
      "languages": [
        "eng"
      ],
      "page_number": 4,
      "filename": "Rule 57.pdf"
    }
  },
  {
    "type": "NarrativeText",
    "element_id": "01215357b044833ca1cdb75ce0ddf72d",
    "text": "Subrule (17): ‘Order the applicant’s release from curatorship.’ The High Court has jurisdiction to order a person’s release 65 from curatorship if the person is domiciled within its area of jurisdiction and his assets are within the area.",
    "metadata": {
      "is_extracted": "true",
      "filetype": "application/pdf",
      "languages": [
        "eng"
      ],
      "page_number": 4,
      "filename": "Rule 57.pdf"
    }
  },
  {
    "type": "NarrativeText",
    "element_id": "b64c726b09db9d425646e81599643253",
    "text": "The ordinary practice is that the applicant must bear the costs of the application, court may order the costs of the application to be borne by the patient’s estate. 67 66 but in appropriate circumstances the",
    "metadata": {
      "is_extracted": "true",
      "filetype": "application/pdf",
      "languages": [
        "eng"
      ],
      "page_number": 4,
      "filename": "Rule 57.pdf"
    }
  },
  {
    "type": "NarrativeText",
    "element_id": "f99cba60609dd97988d5edc41000c3ff",
    "text": "The court will on application and on good cause shown release a curator bonis from his curatorship. The curator will not be 68 released until he has filed accounts to the satisfaction of the Master.",
    "metadata": {
      "is_extracted": "true",
      "filetype": "application/pdf",
      "languages": [
        "eng"
      ],
      "page_number": 4,
      "filename": "Rule 57.pdf"
    }
  },
  {
    "type": "ListItem",
    "element_id": "cc1d3273bf8456a77c126c07e0a9adda",
    "text": "1 The requirements of the rule were carefully considered and applied in Scott v Scott 2021 (2) SA 274 (KZD).",
    "metadata": {
      "is_extracted": "true",
      "filetype": "application/pdf",
      "languages": [
        "eng"
      ],
      "page_number": 4,
      "filename": "Rule 57.pdf"
    }
  },
  {
    "type": "ListItem",
    "element_id": "ec46c2ee0f485975824feaccc4b6baa9",
    "text": "2 Modiba: In re Ruca v Road Accident Fund (unreported, GP case no 73012/13 dated 27 January 2014) at paragraph 33. See also M Letzler & V Vergano ‘Appointing a curator ad litem — Are we applying the law correctly?’ 2014 (June) De Rebus 30.",
    "metadata": {
      "is_extracted": "true",
      "filetype": "application/pdf",
      "languages": [
        "eng"
      ],
      "page_number": 4,
      "filename": "Rule 57.pdf"
    }
  },
  {
    "type": "ListItem",
    "element_id": "72a18991b4a5956fa8680d4e4699c60f",
    "text": "3 Modiba: In re Ruca v Road Accident Fund (unreported, GP case no 73012/13 dated 27 January 2014) at paragraph 46.",
    "metadata": {
      "is_extracted": "true",
      "filetype": "application/pdf",
      "languages": [
        "eng"
      ],
      "page_number": 4,
      "filename": "Rule 57.pdf"
    }
  },
  {
    "type": "ListItem",
    "element_id": "affc2c45e16b5d99a90cb0c02f4e9f74",
    "text": "4 See Van den Berg v Van den Berg 1939 WLD 228.",
    "metadata": {
      "is_extracted": "true",
      "filetype": "application/pdf",
      "languages": [
        "eng"
      ],
      "page_number": 4,
      "filename": "Rule 57.pdf"
    }
  },
  {
    "type": "ListItem",
    "element_id": "0dabcfdbedff13bd922b6cfe987417b5",
    "text": "5 1970 (2) SA 718 (O) at 720E–H. In the particular circumstances of that case, the omission to do so was held not to be fatal.",
    "metadata": {
      "is_extracted": "true",
      "filetype": "application/pdf",
      "languages": [
        "eng"
      ],
      "page_number": 4,
      "filename": "Rule 57.pdf"
    }
  },
  {
    "type": "ListItem",
    "element_id": "7925c3879bab84e919af1df6681de71a",
    "text": "6 Modiba: In re Ruca v Road Accident Fund (unreported, GP case no 73012/13 dated 27 January 2014) at paragraph 45.",
    "metadata": {
      "is_extracted": "true",
      "filetype": "application/pdf",
      "languages": [
        "eng"
      ],
      "page_number": 4,
      "filename": "Rule 57.pdf"
    }
  },
  {
    "type": "ListItem",
    "element_id": "028885501d596bebcdb8fefef8ecb44e",
    "text": "7 Martinson v Brown; Gray NO v Armstrong 1961 (4) SA 107 (C); and see Ex parte Hill 1970 (3) SA 411 (C); Road Accident Fund v Mdeyide (Minister of Transport Intervening) 2008 (1) SA 535 (CC) at 548G–549A; Modiba: In re Ruca v Road Accident Fund (unreported, GP case no 73012/13 dated 27 January 2014) at paragraph 45 and the cases referred to therein.",
    "metadata": {
      "is_extracted": "true",
      "filetype": "application/pdf",
      "languages": [
        "eng"
      ],
      "page_number": 4,
      "filename": "Rule 57.pdf"
    }
  },
  {
    "type": "ListItem",
    "element_id": "5405e82fe082d6ee2a834ede4bef8406",
    "text": "8 Ex parte Hill 1970 (3) SA 411 (C).",
    "metadata": {
      "is_extracted": "true",
      "filetype": "application/pdf",
      "languages": [
        "eng"
      ],
      "page_number": 4,
      "filename": "Rule 57.pdf"
    }
  },
  {
    "type": "ListItem",
    "element_id": "14390a708bd07ef7d09891a7cd54b4ff",
    "text": "9 Ex parte Dixie 1950 (4) SA 748 (W).",
    "metadata": {
      "is_extracted": "true",
      "filetype": "application/pdf",
      "languages": [
        "eng"
      ],
      "page_number": 4,
      "filename": "Rule 57.pdf"
    }
  },
  {
    "type": "ListItem",
    "element_id": "722e600d90664b8753978a0e84f9e7f1",
    "text": "10 Ex parte Powrie 1963 (1) SA 299 (W).",
    "metadata": {
      "is_extracted": "true",
      "filetype": "application/pdf",
      "languages": [
        "eng"
      ],
      "page_number": 4,
      "filename": "Rule 57.pdf"
    }
  },
  {
    "type": "ListItem",
    "element_id": "4be53e442cd39aa24f7c040e346cfd40",
    "text": "11 Ex parte Klopper: In re Klopper 1961 (3) SA 803 (T) at 805E–H; Modiba: In re Ruca v Road Accident Fund (unreported, GP case no 73012/13 dated 27 January 2014) at paragraph 37.",
    "metadata": {
      "is_extracted": "true",
      "filetype": "application/pdf",
      "languages": [
        "eng"
      ],
      "page_number": 4,
      "filename": "Rule 57.pdf"
    }
  },
  {
    "type": "ListItem",
    "element_id": "2c39409ffe799f0530c8040209b0dd2f",
    "text": "12 See Reyneke NO v Mutual & Federal Insurance Co Ltd 1992 (2) SA 417 (T) at 419H–J; and see Modiba: In re Ruca v Road Accident Fund (unreported, GP case no 73012/13 dated 27 January 2014).",
    "metadata": {
      "is_extracted": "true",
      "filetype": "application/pdf",
      "languages": [
        "eng"
      ],
      "page_number": 4,
      "filename": "Rule 57.pdf"
    }
  },
  {
    "type": "ListItem",
    "element_id": "774c18f257c1a0dad6163663eefa000f",
    "text": "13 See, for example, Ex parte Reid: In re M MacGuiness (unreported, WLD dated 9 August 1960); Modiba: In re Ruca v Road Accident Fund (unreported, GP case no 73012/13 dated 27 January 2014) at paragraph 47.",
    "metadata": {
      "is_extracted": "true",
      "filetype": "application/pdf",
      "languages": [
        "eng"
      ],
      "page_number": 4,
      "filename": "Rule 57.pdf"
    }
  },
  {
    "type": "UncategorizedText",
    "element_id": "1b4ffad860297965a240dea120d10b55",
    "text": "14 1976 (2) SA 903 (R).",
    "metadata": {
      "is_extracted": "true",
      "filetype": "application/pdf",
      "languages": [
        "eng"
      ],
      "page_number": 4,
      "filename": "Rule 57.pdf"
    }
  },
  {
    "type": "ListItem",
    "element_id": "4c4006c291a86fc4c044667e9ab11db2",
    "text": "15 1961 (4) SA 79 (N); and see Ex parte Evans: In re Reid 1969 (1) SA 311 (W). In Ex parte Beukes 2011 (5) SA 521 (WCC) the court remarked (at 526H–527D), without deciding the question, that it prima facie seems to have concurrent jurisdiction with the Northern Cape High Court to appoint a curator bonis for the patient under circumstances where the greatest part of the patient’s assets were held within the territorial jurisdiction of the court but the patient resided within the area of jurisdiction of the Northern Cape High Court.",
    "metadata": {
      "is_extracted": "true",
      "filetype": "application/pdf",
      "languages": [
        "eng"
      ],
      "page_number": 4,
      "filename": "Rule 57.pdf"
    }
  },
  {
    "type": "ListItem",
    "element_id": "8bed123e126fe779b3f22e0d372af43b",
    "text": "16 1976 (4) SA 576 (O). See also Ex parte Powrie 1963 (1) SA 299 (W) at 303C; Ex parte Hill 1970 (3) SA 411 (C) at 412D.",
    "metadata": {
      "is_extracted": "true",
      "filetype": "application/pdf",
      "languages": [
        "eng"
      ],
      "page_number": 4,
      "filename": "Rule 57.pdf"
    }
  },
  {
    "type": "ListItem",
    "element_id": "cd161c14542653357b13ef65fe8724e1",
    "text": "17 Modiba: In re Ruca v Road Accident Fund (unreported, GP case no 73012/13 dated 27 January 2014) at paragraph 35 and the authorities referred to therein.",
    "metadata": {
      "is_extracted": "true",
      "filetype": "application/pdf",
      "languages": [
        "eng"
      ],
      "page_number": 4,
      "filename": "Rule 57.pdf"
    }
  },
  {
    "type": "ListItem",
    "element_id": "9111fc1621bf9c142ad8a9c2cc2f4bd2",
    "text": "18 See, for example, Ex parte Hartzenberg 1928 CPD 385; Ex parte Herzberg 1950 (2) SA 62 (C); Ex parte Kotze 1955 (1) SA 665 (C); Ex parte Van der Merwe 1956 (2) SA 113 (C); Ex parte Underhay 1963 (1) SA 22 (O)). In Ex parte Horwood 1960 (4) SA 757 (T) the court held that it might dispense with a curator ad litem if it was satisfied that nothing further could be gained from such an appointment, but on the facts the court declined to do so.",
    "metadata": {
      "is_extracted": "true",
      "filetype": "application/pdf",
      "languages": [
        "eng"
      ],
      "page_number": 4,
      "filename": "Rule 57.pdf"
    }
  },
  {
    "type": "ListItem",
    "element_id": "a8647d01a2430269d5bac2ec57b752f8",
    "text": "19 See Ex parte Tod 1965 (1) SA 262 (D); Reyneke NO v Mutual & Federal Insurance Co Ltd 1992 (2) SA 417 (T) at 418J–419B.",
    "metadata": {
      "is_extracted": "true",
      "filetype": "application/pdf",
      "languages": [
        "eng"
      ],
      "page_number": 4,
      "filename": "Rule 57.pdf"
    }
  },
  {
    "type": "ListItem",
    "element_id": "14296216065fb2645d1a62dc75ee541f",
    "text": "20 Ex parte Papendorp 1932 CPD 167; Ex parte McLinden 1945 OPD 96; Ex parte Estate Van Rensburg 1948 (2) SA 753 (O) at 754; Delius v Delius 1960 (1) SA 270 (N) at 273D; Ex parte Van der Linde 1970 (2) SA 718 (O) at 720C.",
    "metadata": {
      "is_extracted": "true",
      "filetype": "application/pdf",
      "languages": [
        "eng"
      ],
      "page_number": 4,
      "filename": "Rule 57.pdf"
    }
  },
  {
    "type": "ListItem",
    "element_id": "ae6c3c107390b338ad839d2adfee3e97",
    "text": "21 Ex parte Papendorp 1932 CPD 167; Lockwood v Lockwood 1935 EDL 1; Ex parte McLinden 1945 OPD 96; Delius v Delius 1960 (1) SA 270 (N).",
    "metadata": {
      "is_extracted": "true",
      "filetype": "application/pdf",
      "languages": [
        "eng"
      ],
      "page_number": 4,
      "filename": "Rule 57.pdf"
    }
  },
  {
    "type": "UncategorizedText",
    "element_id": "6dbd38dabba8e921f9a870dac3217037",
    "text": "ERE",
    "metadata": {
      "filetype": "application/pdf",
      "languages": [
        "eng"
      ],
      "page_number": 4,
      "filename": "Rule 57.pdf"
    }
  },
  {
    "type": "ListItem",
    "element_id": "67927ac2b01ccff0d239b4fe58354bf6",
    "text": "22 1948 (2) SA 219 (O).",
    "metadata": {
      "is_extracted": "true",
      "filetype": "application/pdf",
      "languages": [
        "eng"
      ],
      "page_number": 4,
      "filename": "Rule 57.pdf"
    }
  },
  {
    "type": "ListItem",
    "element_id": "1cc88d8917c69a87645a3dbb4233f56e",
    "text": "23 Ex parte Groenewald 1963 (3) SA 588 (C).",
    "metadata": {
      "is_extracted": "true",
      "filetype": "application/pdf",
      "languages": [
        "eng"
      ],
      "page_number": 4,
      "filename": "Rule 57.pdf"
    }
  },
  {
    "type": "ListItem",
    "element_id": "5dbba453fac2fbd8670daf23ecd448cd",
    "text": "24 Ex parte Dixie 1950 (4) SA 748 (W).",
    "metadata": {
      "is_extracted": "true",
      "filetype": "application/pdf",
      "languages": [
        "eng"
      ],
      "page_number": 4,
      "filename": "Rule 57.pdf"
    }
  },
  {
    "type": "ListItem",
    "element_id": "9d1c70d47225769baa51b168ab18d6ac",
    "text": "25 McArthur v Marshall 1979 (2) SA 574 (C).",
    "metadata": {
      "is_extracted": "true",
      "filetype": "application/pdf",
      "languages": [
        "eng"
      ],
      "page_number": 4,
      "filename": "Rule 57.pdf"
    }
  },
  {
    "type": "ListItem",
    "element_id": "fc24d12b4a8fc1eb552303f6b3aafed9",
    "text": "26 Judin v Wedgwood 2003 (5) SA 472 (W) at 461I–477D–E; Modiba: In re Ruca v Road Accident Fund (unreported, GP case no 73012/13 dated 27 January 2014) at paragraph 32 and the authorities there referred to; H In re: Taute In re: H v H (unreported, GJ case no 34770/2018 dated 18 August 2022) at paragraphs [30] and [42].",
    "metadata": {
      "is_extracted": "true",
      "filetype": "application/pdf",
      "languages": [
        "eng"
      ],
      "page_number": 4,
      "filename": "Rule 57.pdf"
    }
  },
  {
    "type": "ListItem",
    "element_id": "fa5bf4e0a20fac91b67054d075dfb5c0",
    "text": "27 Ex parte Hendrikse: In re Louw 1990 (3) SA 227 (C) at 229B.",
    "metadata": {
      "is_extracted": "true",
      "filetype": "application/pdf",
      "languages": [
        "eng"
      ],
      "page_number": 4,
      "filename": "Rule 57.pdf"
    }
  },
  {
    "type": "Footer",
    "element_id": "4cfbee6b5e72a16e77b098269e96126f",
    "text": "© 2025 Juta and Company (Pty) Ltd.",
    "metadata": {
      "is_extracted": "true",
      "filetype": "application/pdf",
      "languages": [
        "eng"
      ],
      "page_number": 4,
      "filename": "Rule 57.pdf"
    }
  },
  {
    "type": "Footer",
    "element_id": "58d048685450793e228c8614f4f5ffbe",
    "text": "Downloaded: Mon Feb 17 2025 12:10:40 GMT+0200 (South Africa Standard Time)",
    "metadata": {
      "is_extracted": "true",
      "filetype": "application/pdf",
      "languages": [
        "eng"
      ],
      "page_number": 4,
      "filename": "Rule 57.pdf"
    }
  },
  {
    "type": "PageBreak",
    "element_id": "3a9bd49f191ad85ccf38e4ec1ef9d571",
    "text": "",
    "metadata": {
      "languages": [
        "eng"
      ],
      "filename": "Rule 57.pdf",
      "filetype": "application/pdf"
    }
  },
  {
    "type": "ListItem",
    "element_id": "1e02e0b345acd0fad619846d28666ecf",
    "text": "28 Ex parte Maritz; Ex parte De Klerk 1968 (4) SA 130 (C) at 134H; Ex parte Hendrikse: In re Louw 1990 (3) SA 227 (C) at 229.",
    "metadata": {
      "is_extracted": "true",
      "filetype": "application/pdf",
      "languages": [
        "eng"
      ],
      "page_number": 5,
      "filename": "Rule 57.pdf"
    }
  },
  {
    "type": "ListItem",
    "element_id": "c788768942688dc74cbf6e17df351e95",
    "text": "29 Ex parte Hendrikse: In re Louw 1990 (3) SA 227 (C) at 229G. See also Ex parte Griesel 1948 (2) SA 219 (O) at 220; Ex parte Campher 1951 (3) SA 248 (C) at 252A.",
    "metadata": {
      "is_extracted": "true",
      "filetype": "application/pdf",
      "languages": [
        "eng"
      ],
      "page_number": 5,
      "filename": "Rule 57.pdf"
    }
  },
  {
    "type": "ListItem",
    "element_id": "f0962b8a35345727db17aae5026b8d90",
    "text": "30 Ex parte Maritz; Ex parte De Klerk 1968 (4) SA 130 (C) at 134H.",
    "metadata": {
      "is_extracted": "true",
      "filetype": "application/pdf",
      "languages": [
        "eng"
      ],
      "page_number": 5,
      "filename": "Rule 57.pdf"
    }
  },
  {
    "type": "ListItem",
    "element_id": "f8a9a0519a0a5651a9ecdc1199c080d9",
    "text": "31 1921 TPD 514 at 516.",
    "metadata": {
      "is_extracted": "true",
      "filetype": "application/pdf",
      "languages": [
        "eng"
      ],
      "page_number": 5,
      "filename": "Rule 57.pdf"
    }
  },
  {
    "type": "ListItem",
    "element_id": "d155b3ad098d3169e828773542125076",
    "text": "32 Unreported, GP case no 73012/13 dated 27 January 2014 at paragraph 35.",
    "metadata": {
      "is_extracted": "true",
      "filetype": "application/pdf",
      "languages": [
        "eng"
      ],
      "page_number": 5,
      "filename": "Rule 57.pdf"
    }
  },
  {
    "type": "ListItem",
    "element_id": "c2616502113296a4f66525535d7f1dd3",
    "text": "33 Ex parte Campher 1951 (3) SA 248 (C) at 252A.",
    "metadata": {
      "is_extracted": "true",
      "filetype": "application/pdf",
      "languages": [
        "eng"
      ],
      "page_number": 5,
      "filename": "Rule 57.pdf"
    }
  },
  {
    "type": "ListItem",
    "element_id": "17b1379e9bd316b23d30388e4dbf3c1a",
    "text": "34 Ex parte Griesel 1948 (2) SA 219 (O) at 221; Ex parte Estate Van Rensburg 1948 (2) SA 753 (O); Ex parte Van der Linde 1970 (2) SA 718 (O) at 721G; and see Ex parte Campher 1951 (3) SA 248 (C) at 252A.",
    "metadata": {
      "is_extracted": "true",
      "filetype": "application/pdf",
      "languages": [
        "eng"
      ],
      "page_number": 5,
      "filename": "Rule 57.pdf"
    }
  },
  {
    "type": "ListItem",
    "element_id": "87f95ea12c919a52401fc0e89dc71108",
    "text": "35 Ex parte Glendale Sugar Millers (Pty) Ltd 1973 (2) SA 653 (N) at 659H; Modiba: In re Ruca v Road Accident Fund (unreported, GP case no 73012/13 dated 27 January 2014) at paragraph 37.",
    "metadata": {
      "is_extracted": "true",
      "filetype": "application/pdf",
      "languages": [
        "eng"
      ],
      "page_number": 5,
      "filename": "Rule 57.pdf"
    }
  },
  {
    "type": "ListItem",
    "element_id": "d956ca48c21a12abbfa7f89d43a445ed",
    "text": "36 See, for example, In re Bathgate (1858) 3 Searle 187; Ex parte Mallach 1921 TPD 514 at 516; Ex parte Ventham 1931 WLD 47; Ex parte Comins 1951 (2) SA 249 (C); Ex parte Colborne 1954 (4) SA 198 (SR).",
    "metadata": {
      "is_extracted": "true",
      "filetype": "application/pdf",
      "languages": [
        "eng"
      ],
      "page_number": 5,
      "filename": "Rule 57.pdf"
    }
  },
  {
    "type": "ListItem",
    "element_id": "c38f4220c261760f5265f5bd678e8c92",
    "text": "37 Ex parte Campher 1951 (3) SA 248 (C) at 252C.",
    "metadata": {
      "is_extracted": "true",
      "filetype": "application/pdf",
      "languages": [
        "eng"
      ],
      "page_number": 5,
      "filename": "Rule 57.pdf"
    }
  },
  {
    "type": "ListItem",
    "element_id": "56d1c397543e2ce34e798ab1aa4e430c",
    "text": "38 Ex parte Campher 1951 (3) SA 248 (C) at 252D.",
    "metadata": {
      "is_extracted": "true",
      "filetype": "application/pdf",
      "languages": [
        "eng"
      ],
      "page_number": 5,
      "filename": "Rule 57.pdf"
    }
  },
  {
    "type": "ListItem",
    "element_id": "c39baf8282f319e24fc55c707a314793",
    "text": "39 Ex parte Campher 1951 (3) SA 248 (C) at 252E; Modiba: In re Ruca v Road Accident Fund (unreported, GP case no 73012/13 dated 27 January 2014) at paragraph 48.",
    "metadata": {
      "is_extracted": "true",
      "filetype": "application/pdf",
      "languages": [
        "eng"
      ],
      "page_number": 5,
      "filename": "Rule 57.pdf"
    }
  },
  {
    "type": "ListItem",
    "element_id": "e43d31dd8aa75489da20fc6c9f66639e",
    "text": "40 See Steyn v Steyn 1972 (4) SA 151 (NC) at 152F.",
    "metadata": {
      "is_extracted": "true",
      "filetype": "application/pdf",
      "languages": [
        "eng"
      ],
      "page_number": 5,
      "filename": "Rule 57.pdf"
    }
  },
  {
    "type": "UncategorizedText",
    "element_id": "51c18e8969db21eeab3ab6ea1aba9be2",
    "text": "IERE RIE",
    "metadata": {
      "filetype": "application/pdf",
      "languages": [
        "eng"
      ],
      "page_number": 5,
      "filename": "Rule 57.pdf"
    }
  },
  {
    "type": "ListItem",
    "element_id": "986d4734bc20715e1ffa112155ae10e6",
    "text": "41 Ex parte Campher 1951 (3) SA 248 (C) at 252C; and see Du Plessis NO v Strauss 1988 (2) SA 105 (A) at 145H–146D.",
    "metadata": {
      "is_extracted": "true",
      "filetype": "application/pdf",
      "languages": [
        "eng"
      ],
      "page_number": 5,
      "filename": "Rule 57.pdf"
    }
  },
  {
    "type": "ListItem",
    "element_id": "c67315989c8e7af31770900f0e0cce28",
    "text": "42 Ex parte Beukes 2011 (5) SA 521 (WCC) at 526E–F; Modiba: In re Ruca v Road Accident Fund (unreported, GP case no 73012/13 dated 27 January 2014) at paragraph 39.",
    "metadata": {
      "is_extracted": "true",
      "filetype": "application/pdf",
      "languages": [
        "eng"
      ],
      "page_number": 5,
      "filename": "Rule 57.pdf"
    }
  },
  {
    "type": "ListItem",
    "element_id": "361e26aa8968be2d211d3c6230db96ad",
    "text": "43 Ex parte Beukes 2011 (5) SA 521 (WCC) at 525D.",
    "metadata": {
      "is_extracted": "true",
      "filetype": "application/pdf",
      "languages": [
        "eng"
      ],
      "page_number": 5,
      "filename": "Rule 57.pdf"
    }
  },
  {
    "type": "ListItem",
    "element_id": "c9251f716864cab38b326b846a304216",
    "text": "44 Ex parte Beukes 2011 (5) SA 521 (WCC) at 525D–E.",
    "metadata": {
      "is_extracted": "true",
      "filetype": "application/pdf",
      "languages": [
        "eng"
      ],
      "page_number": 5,
      "filename": "Rule 57.pdf"
    }
  },
  {
    "type": "ListItem",
    "element_id": "ec6ce970e341dcee8d40920ba364b625",
    "text": "45 Ex parte Beukes 2011 (5) SA 521 (WCC) at 525E.",
    "metadata": {
      "is_extracted": "true",
      "filetype": "application/pdf",
      "languages": [
        "eng"
      ],
      "page_number": 5,
      "filename": "Rule 57.pdf"
    }
  },
  {
    "type": "ListItem",
    "element_id": "9f52846d4812546f3062cf1c256474f6",
    "text": "46 Modiba: In re Ruca v Road Accident Fund (unreported, GP case no 73012/13 dated 27 January 2014) at paragraph 40.",
    "metadata": {
      "is_extracted": "true",
      "filetype": "application/pdf",
      "languages": [
        "eng"
      ],
      "page_number": 5,
      "filename": "Rule 57.pdf"
    }
  },
  {
    "type": "ListItem",
    "element_id": "f2d3e028237bc19c20343b3323747ef4",
    "text": "47 Ex parte Davidson 1981 (3) SA 575 (D); Ex parte Smit: In re Boedel Smit 1983 (3) SA 438 (T). It should, however, be kept in mind that the purpose of furnishing security is to protect the interests of the de cujus (see Bouwer NO v Saambou Bank Bpk 1993 (4) SA 492 (T) at 497H–J).",
    "metadata": {
      "is_extracted": "true",
      "filetype": "application/pdf",
      "languages": [
        "eng"
      ],
      "page_number": 5,
      "filename": "Rule 57.pdf"
    }
  },
  {
    "type": "ListItem",
    "element_id": "08858a846baf5dfd9b695c472dde10cf",
    "text": "48 See Ex parte Campher 1951 (3) SA 248 (C) at 252F; Ex parte Maritz; Ex parte De Klerk 1968 (4) SA 130 (C) at 134; Ex parte Hendrikse: In re Louw 1990 (3) SA 227 (C) at 229C.",
    "metadata": {
      "is_extracted": "true",
      "filetype": "application/pdf",
      "languages": [
        "eng"
      ],
      "page_number": 5,
      "filename": "Rule 57.pdf"
    }
  },
  {
    "type": "ListItem",
    "element_id": "c6801ba0ab41aef01f0b777b433a4384",
    "text": "49 See Ex parte Comins 1951 (2) SA 249 (C) in which the court laid down as a new rule of practice that such evidence may, by leave of the court, be adduced on affidavit.",
    "metadata": {
      "is_extracted": "true",
      "filetype": "application/pdf",
      "languages": [
        "eng"
      ],
      "page_number": 5,
      "filename": "Rule 57.pdf"
    }
  },
  {
    "type": "ListItem",
    "element_id": "e447f61bf88e8f97070b7b9681e8177d",
    "text": "50 Ex parte Klopper: In re Klopper 1961 (3) SA 803 (T) at 805E–H. See also Modiba: In re Ruca v Road Accident Fund (unreported, GP case no 73012/13 dated 27 January 2014) at paragraph 37.",
    "metadata": {
      "is_extracted": "true",
      "filetype": "application/pdf",
      "languages": [
        "eng"
      ],
      "page_number": 5,
      "filename": "Rule 57.pdf"
    }
  },
  {
    "type": "ListItem",
    "element_id": "c92059ac5f267d74a96216bf19933d29",
    "text": "51 Ex parte Hulett 1968 (4) SA 172 (D) at 174D.",
    "metadata": {
      "is_extracted": "true",
      "filetype": "application/pdf",
      "languages": [
        "eng"
      ],
      "page_number": 5,
      "filename": "Rule 57.pdf"
    }
  },
  {
    "type": "ListItem",
    "element_id": "d862b2b32d9e1871325893e71e93cbbb",
    "text": "52 Other cases to which reference may be made are Ex parte Powrie 1963 (1) SA 299 (W); Ex parte Kelly NO: In re Curatorship Estate Rosenfeld 1972 (2) SA 561 (T); Nyathi v Nyathi 1976 (4) SA 43 (R); Ex parte Ganga 1979 (1) SA 586 (N).",
    "metadata": {
      "is_extracted": "true",
      "filetype": "application/pdf",
      "languages": [
        "eng"
      ],
      "page_number": 5,
      "filename": "Rule 57.pdf"
    }
  },
  {
    "type": "ListItem",
    "element_id": "a4bf475be55dce2428e83c56e49f43a8",
    "text": "53 1965 (3) SA 553 (W) at 557.",
    "metadata": {
      "is_extracted": "true",
      "filetype": "application/pdf",
      "languages": [
        "eng"
      ],
      "page_number": 5,
      "filename": "Rule 57.pdf"
    }
  },
  {
    "type": "UncategorizedText",
    "element_id": "76b9ae582b2cd84dfd667cd813c3a339",
    "text": "BIIEIIIL",
    "metadata": {
      "filetype": "application/pdf",
      "languages": [
        "eng"
      ],
      "page_number": 5,
      "filename": "Rule 57.pdf"
    }
  },
  {
    "type": "ListItem",
    "element_id": "8e41b554abc5315a73d52e32ac7c6f2e",
    "text": "54 1968 (1) SA 33 (T) at 37–8.",
    "metadata": {
      "is_extracted": "true",
      "filetype": "application/pdf",
      "languages": [
        "eng"
      ],
      "page_number": 5,
      "filename": "Rule 57.pdf"
    }
  },
  {
    "type": "ListItem",
    "element_id": "3ab21368c6e6d0dd2d2a6f75db9a16ec",
    "text": "55 1968 (4) SA 172 (D) at 175–6.",
    "metadata": {
      "is_extracted": "true",
      "filetype": "application/pdf",
      "languages": [
        "eng"
      ],
      "page_number": 5,
      "filename": "Rule 57.pdf"
    }
  },
  {
    "type": "ListItem",
    "element_id": "ee17879fd9a17b4faf2160cad967bb6e",
    "text": "56 1971 (3) SA 376 (D) at 379–81.",
    "metadata": {
      "is_extracted": "true",
      "filetype": "application/pdf",
      "languages": [
        "eng"
      ],
      "page_number": 5,
      "filename": "Rule 57.pdf"
    }
  },
  {
    "type": "ListItem",
    "element_id": "f5e1a95bd56a38e0ba4a56d5e2966cd1",
    "text": "57 1992 (2) SA 417 (T) at 422.",
    "metadata": {
      "is_extracted": "true",
      "filetype": "application/pdf",
      "languages": [
        "eng"
      ],
      "page_number": 5,
      "filename": "Rule 57.pdf"
    }
  },
  {
    "type": "ListItem",
    "element_id": "1c435187bc98864f8d40036ba03e9281",
    "text": "58 1995 (4) SA 101 (D).",
    "metadata": {
      "is_extracted": "true",
      "filetype": "application/pdf",
      "languages": [
        "eng"
      ],
      "page_number": 5,
      "filename": "Rule 57.pdf"
    }
  },
  {
    "type": "ListItem",
    "element_id": "6e7a47426186e38a30c25ad979567ca2",
    "text": "59 1988 (1) SA 790 (C).",
    "metadata": {
      "is_extracted": "true",
      "filetype": "application/pdf",
      "languages": [
        "eng"
      ],
      "page_number": 5,
      "filename": "Rule 57.pdf"
    }
  },
  {
    "type": "ListItem",
    "element_id": "4f7764bd7ea46d7697ee7337ab682776",
    "text": "60 Ex parte Wilson: In re Morison 1991 (4) SA 774 (T) at 779J–780A.",
    "metadata": {
      "is_extracted": "true",
      "filetype": "application/pdf",
      "languages": [
        "eng"
      ],
      "page_number": 5,
      "filename": "Rule 57.pdf"
    }
  },
  {
    "type": "ListItem",
    "element_id": "e89fa5f725eb672a8c058cc3de5784a0",
    "text": "61 See, for example, the order as to costs in Ex parte Hulett 1968 (4) SA 172 (D) at 176C. See also Ex parte Du Toit: In re Curatorship Estate Schwab 1968 (1) SA 33 (T) at 38; Ex parte Wagner NO: In re De Bie 1988 (1) SA 790 (C) at 791E.",
    "metadata": {
      "is_extracted": "true",
      "filetype": "application/pdf",
      "languages": [
        "eng"
      ],
      "page_number": 5,
      "filename": "Rule 57.pdf"
    }
  },
  {
    "type": "ListItem",
    "element_id": "7ba5582881926221844724571db5caf8",
    "text": "62 See the order as to costs in Ex parte Wilson: In re Morison 1991 (4) SA 774 (T) at 780C.",
    "metadata": {
      "is_extracted": "true",
      "filetype": "application/pdf",
      "languages": [
        "eng"
      ],
      "page_number": 5,
      "filename": "Rule 57.pdf"
    }
  },
  {
    "type": "ListItem",
    "element_id": "86bad9b1dac8b5cb940e85de9a013ec0",
    "text": "63 Reyneke NO v Mutual & Federal Insurance Co Ltd 1992 (2) SA 417 (T) at 419H–J. Included in the award of damages would also be the costs of the administration by the curator bonis of the injured party’s affairs and the curator’s remuneration.",
    "metadata": {
      "is_extracted": "true",
      "filetype": "application/pdf",
      "languages": [
        "eng"
      ],
      "page_number": 5,
      "filename": "Rule 57.pdf"
    }
  },
  {
    "type": "UncategorizedText",
    "element_id": "43f5947d4d5f16e39ddd7cda51fc871e",
    "text": "64 See Van den Berg v Van den Berg 1939 WLD 228.",
    "metadata": {
      "is_extracted": "true",
      "filetype": "application/pdf",
      "languages": [
        "eng"
      ],
      "page_number": 5,
      "filename": "Rule 57.pdf"
    }
  },
  {
    "type": "ListItem",
    "element_id": "f44c144ec35d0d4fc0726558760f99b2",
    "text": "65 Ex parte Quigly 1957 (4) SA 169 (N). Though in this case the patient was also resident within the court’s area, this would not seem to be a requirement in view of the decision in Ex parte Berry: In re Berry 1961 (4) SA 79 (N) in which it was held that any division of the Supreme Court (i e the High Court) has jurisdiction to declare incapable of managing his affairs and place under curatorship any person who is domiciled within its area of jurisdiction or whose assets are within such area, notwithstanding that he himself is not within the area.",
    "metadata": {
      "is_extracted": "true",
      "filetype": "application/pdf",
      "languages": [
        "eng"
      ],
      "page_number": 5,
      "filename": "Rule 57.pdf"
    }
  },
  {
    "type": "ListItem",
    "element_id": "7bfd9a951047ba9b22c1fec3831228a7",
    "text": "66 Ex parte Bate 1928 CPD 186.",
    "metadata": {
      "is_extracted": "true",
      "filetype": "application/pdf",
      "languages": [
        "eng"
      ],
      "page_number": 5,
      "filename": "Rule 57.pdf"
    }
  },
  {
    "type": "ListItem",
    "element_id": "adbff09fe4dcd8d6e4641a7983b1418b",
    "text": "67 Ex parte Place 1930 EDL 149; Ex parte Smuts 1935 TPD 23; Ex parte African Board of Executors and Trust Co Ltd 1939 TPD 37; The Master v White 1946 CPD 24; Ex parte Frost 1956 (4) SA 797 (T).",
    "metadata": {
      "is_extracted": "true",
      "filetype": "application/pdf",
      "languages": [
        "eng"
      ],
      "page_number": 5,
      "filename": "Rule 57.pdf"
    }
  },
  {
    "type": "ListItem",
    "element_id": "251ee4e87e1568d72ea009b6bd3a756c",
    "text": "68 Ex parte Mann 1941 EDL 159; Ex parte Bowie 1842 EDL 5.",
    "metadata": {
      "is_extracted": "true",
      "filetype": "application/pdf",
      "languages": [
        "eng"
      ],
      "page_number": 5,
      "filename": "Rule 57.pdf"
    }
  },
  {
    "type": "Footer",
    "element_id": "b82f8266ce087dd6cbf3b95b8dac5e05",
    "text": "© 2025 Juta and Company (Pty) Ltd. Downloaded: Mon Feb 17 2025 12:10:40 GMT+0200 (South Africa Standard Time)",
    "metadata": {
      "is_extracted": "true",
      "filetype": "application/pdf",
      "languages": [
        "eng"
      ],
      "page_number": 5,
      "filename": "Rule 57.pdf"
    }
  },
  {
    "type": "PageBreak",
    "element_id": "2e6c343df2a53181f450b26a6d48de20",
    "text": "",
    "metadata": {
      "languages": [
        "eng"
      ],
      "filename": "Rule 57.pdf",
      "filetype": "application/pdf"
    }
  }
]